chromecodepdf.py
chromecodepdf-0.1.0a1.dist-info/licenses/LICENSE
chromecodepdf-0.1.0a1.dist-info/METADATA
chromecodepdf-0.1.0a1.dist-info/WHEEL
chromecodepdf-0.1.0a1.dist-info/top_level.txt
chromecodepdf-0.1.0a1.dist-info/RECORD
