Metadata-Version: 2.4
Name: chromecodepdf
Version: 0.1.0a1
Summary: A Python script that converts code files into syntax-highlighted PDF documents using Chrome and Pygments.
Author-email: Jifeng Wu <jifengwu2k@gmail.com>
License-Expression: MIT
Project-URL: Homepage, https://github.com/jifengwu2k/chromecodepdf
Project-URL: Bug Tracker, https://github.com/jifengwu2k/chromecodepdf/issues
Classifier: Programming Language :: Python :: 2
Classifier: Programming Language :: Python :: 3
Classifier: Operating System :: OS Independent
Requires-Python: >=2
License-File: LICENSE
Requires-Dist: ctypes-unicode-proclaunch
Requires-Dist: get-chrome-paths
Requires-Dist: pygments
Requires-Dist: textcompat
Dynamic: license-file
